lcu_connectorpy/__init__.py
lcu_connectorpy/connect.py
lcu_connectorpy-1.1.0.dist-info/entry_points.txt
lcu_connectorpy-1.1.0.dist-info/LICENSE
lcu_connectorpy-1.1.0.dist-info/WHEEL
lcu_connectorpy-1.1.0.dist-info/METADATA
lcu_connectorpy-1.1.0.dist-info/RECORD
