Metadata-Version: 2.1
Name: lcu-connectorpy
Version: 1.1.0
Summary: An interface for the LoL client API.
Home-page: https://github.com/Zer0897/lcu_connectorpy
License: MIT
Keywords: league-of-legends,api-client
Author: Noah
Author-email: noah@coronasoftware.net
Requires-Python: >=3.6
Classifier: License :: OSI Approved :: MIT License
Classifier: Programming Language :: Python :: 3
Classifier: Programming Language :: Python :: 3.6
Classifier: Programming Language :: Python :: 3.7
Requires-Dist: psutil (>=5.6,<6.0)
Requires-Dist: pyyaml (>=5.1,<6.0)
Requires-Dist: watchdog (>=0.9.0,<0.10.0)
Project-URL: Documentation, https://zer0897.github.io/lcu_connectorpy/lcu_connectorpy/index.html
Project-URL: Repository, https://github.com/Zer0897/lcu_connectorpy
